.gitignore
MANIFEST.in
README.md
__init__.py
setup.py
tk_hauteskundeak/__init__.py
tk_hauteskundeak/admin.py
tk_hauteskundeak/api_views.py
tk_hauteskundeak/datuakKargatu.py
tk_hauteskundeak/homecards.py
tk_hauteskundeak/meta.py
tk_hauteskundeak/models.py
tk_hauteskundeak/serializers.py
tk_hauteskundeak/urls.py
tk_hauteskundeak/views.py
tk_hauteskundeak.egg-info/PKG-INFO
tk_hauteskundeak.egg-info/SOURCES.txt
tk_hauteskundeak.egg-info/dependency_links.txt
tk_hauteskundeak.egg-info/not-zip-safe
tk_hauteskundeak.egg-info/requires.txt
tk_hauteskundeak.egg-info/top_level.txt
tk_hauteskundeak/api/utils/__init__.py
tk_hauteskundeak/api/utils/bn_araba.py
tk_hauteskundeak/api/utils/bn_bizkaia.py
tk_hauteskundeak/api/utils/bn_gipuzkoa.py
tk_hauteskundeak/api/utils/bn_nafarroa.py
tk_hauteskundeak/api/utils/candidates.py
tk_hauteskundeak/api/utils/europa.py
tk_hauteskundeak/api/utils/eusko_jaurlaritza.py
tk_hauteskundeak/api/utils/ministerioa_kongresua.py
tk_hauteskundeak/api/utils/ministerioa_udalak.py
tk_hauteskundeak/hauteskunde-emaitzak/aldundiak1979.csv
tk_hauteskundeak/hauteskunde-emaitzak/aldundiak1983.csv
tk_hauteskundeak/hauteskunde-emaitzak/aldundiak1987.csv
tk_hauteskundeak/hauteskunde-emaitzak/aldundiak1991.csv
tk_hauteskundeak/hauteskunde-emaitzak/aldundiak1995.csv
tk_hauteskundeak/hauteskunde-emaitzak/aldundiak1999.csv
tk_hauteskundeak/hauteskunde-emaitzak/aldundiak2003.csv
tk_hauteskundeak/hauteskunde-emaitzak/aldundiak2007.csv
tk_hauteskundeak/hauteskunde-emaitzak/aldundiak2011.csv
tk_hauteskundeak/hauteskunde-emaitzak/aldundiak2015.csv
tk_hauteskundeak/hauteskunde-emaitzak/aldundiak2019.csv
tk_hauteskundeak/hauteskunde-emaitzak/espainia-012019.csv
tk_hauteskundeak/hauteskunde-emaitzak/espainia-022019.csv
tk_hauteskundeak/hauteskunde-emaitzak/espainia1977.csv
tk_hauteskundeak/hauteskunde-emaitzak/espainia1979.csv
tk_hauteskundeak/hauteskunde-emaitzak/espainia1982.csv
tk_hauteskundeak/hauteskunde-emaitzak/espainia1986.csv
tk_hauteskundeak/hauteskunde-emaitzak/espainia1989.csv
tk_hauteskundeak/hauteskunde-emaitzak/espainia1993.csv
tk_hauteskundeak/hauteskunde-emaitzak/espainia1996.csv
tk_hauteskundeak/hauteskunde-emaitzak/espainia2000.csv
tk_hauteskundeak/hauteskunde-emaitzak/espainia2004.csv
