Metadata-Version: 2.1
Name: tk_hauteskundeak
Version: 1.34
Summary: Tokikerako hauteskundeetarako tresna
Home-page: 
Author: jargarate
Author-email: jargarate@codesyntax.com
Requires-Dist: django-highcharts==0.1.7
Requires-Dist: django-colorfield==0.7.2
Requires-Dist: xmltodict==0.13.0
Requires-Dist: django-object-actions==4.1.0
Requires-Dist: django-import-export
